photoprism_captioner/__init__.py
photoprism_captioner/main.py
photoprism_captioner/photoprism_client.py
photoprism_captioner/utils.py
photoprism_captioner-0.1.3.dist-info/METADATA
photoprism_captioner-0.1.3.dist-info/WHEEL
photoprism_captioner-0.1.3.dist-info/entry_points.txt
photoprism_captioner-0.1.3.dist-info/top_level.txt
photoprism_captioner-0.1.3.dist-info/RECORD
