Metadata-Version: 2.4
Name: photoprism-captioner
Version: 0.1.3
Summary: A tool for adding captions to PhotoPrism photos
Author-email: djbios <djbios@djbios.org>
License: MIT
Requires-Python: >=3.11
Requires-Dist: pillow>=11.3.0
Requires-Dist: requests>=2.32.4
Provides-Extra: local
Requires-Dist: torch>=2.0.0; extra == "local"
Requires-Dist: transformers>=4.30.0; extra == "local"
Provides-Extra: remote
Requires-Dist: litellm>=1.0.0; extra == "remote"
